{
	"configurations" : 
	[
		{
			"directories" : 
			[
				{
					"build" : ".",
					"childIndexes" : 
					[
						1
					],
					"jsonFile" : "directory-.-Debug-f5ebdc15457944623624.json",
					"minimumCMakeVersion" : 
					{
						"string" : "3.20"
					},
					"projectIndex" : 0,
					"source" : ".",
					"targetIndexes" : 
					[
						0
					]
				},
				{
					"build" : "src/slib",
					"jsonFile" : "directory-src.slib-Debug-ce64893d77e41dcc7ba3.json",
					"minimumCMakeVersion" : 
					{
						"string" : "3.20"
					},
					"parentIndex" : 0,
					"projectIndex" : 0,
					"source" : "src/slib",
					"targetIndexes" : 
					[
						1
					]
				}
			],
			"name" : "Debug",
			"projects" : 
			[
				{
					"directoryIndexes" : 
					[
						0,
						1
					],
					"name" : "Machine-Learning-Freestanding",
					"targetIndexes" : 
					[
						0,
						1
					]
				}
			],
			"targets" : 
			[
				{
					"directoryIndex" : 0,
					"id" : "main::@6890427a1f51a3e7e1df",
					"jsonFile" : "target-main-Debug-ca368746e51d3934f88c.json",
					"name" : "main",
					"projectIndex" : 0
				},
				{
					"directoryIndex" : 1,
					"id" : "slib::@ade86f367e9dc75ff8d8",
					"jsonFile" : "target-slib-Debug-be9ad32b4fdca5b9b886.json",
					"name" : "slib",
					"projectIndex" : 0
				}
			]
		}
	],
	"kind" : "codemodel",
	"paths" : 
	{
		"build" : "/home/freddie/CLionProjects/Machine-Learning-Freestanding/cmake-build-debug",
		"source" : "/home/freddie/CLionProjects/Machine-Learning-Freestanding"
	},
	"version" : 
	{
		"major" : 2,
		"minor" : 8
	}
}
